CHANGELOG.org
LICENSE
tasktools/__init__.py
tasktools/assignator.py
tasktools/assignator.py~
tasktools/async_queue.py
tasktools/scheduler.py
tasktools/taskloop.py
tasktools/tools.py
tasktools-1.2.0.dist-info/LICENSE
tasktools-1.2.0.dist-info/METADATA
tasktools-1.2.0.dist-info/LICENSE.txt
tasktools-1.2.0.dist-info/WHEEL
tasktools-1.2.0.dist-info/RECORD
